catd/Doc.py
catd/Topic.py
catd/WordNet.py
catd/WordNode.py
catd/__init__.py
catd/__main__.py
catd/util/__init__.py
catd/util/util.py
catd-0.5.0.dist-info/LICENSE
catd-0.5.0.dist-info/METADATA
catd-0.5.0.dist-info/WHEEL
catd-0.5.0.dist-info/top_level.txt
catd-0.5.0.dist-info/RECORD
