Metadata-Version: 2.1
Name: catd
Version: 0.5.0
Summary: A Chinese co-word analysis with topic discovery package
Home-page: https://github.com/dqwerter/catd
Author: Wang Qin
Author-email: wangqin0@outlook.com
License: UNKNOWN
Download-URL: https://github.com/dqwerter/catd/archive/0.5.0.tar.gz
Platform: UNKNOWN
Classifier: Development Status :: 4 - Beta
Classifier: Environment :: Console
Classifier: Intended Audience :: Science/Research
Classifier: Programming Language :: Python :: 3
Classifier: License :: OSI Approved :: MIT License
Classifier: Operating System :: OS Independent
Requires-Python: >=3.6
License-File: LICENSE
Requires-Dist: jieba
Requires-Dist: gensim
Requires-Dist: wordcloud
Requires-Dist: matplotlib
Requires-Dist: sqlite3
